mbasic-1.0.955.dist-info/licenses/LICENSE
src/ast_nodes.py
src/basic_builtins.py
src/bot_protection.py
src/case_keeper.py
src/case_string_handler.py
src/codegen_backend.py
src/codegen_js_backend.py
src/debug_logger.py
src/docs_config.py
src/error_codes.py
src/error_logger.py
src/file_io.py
src/immediate_executor.py
src/input_sanitizer.py
src/interactive.py
src/interpreter.py
src/keyword_case_manager.py
src/lexer.py
src/multiuser_config.py
src/parser.py
src/pc.py
src/position_serializer.py
src/resource_limits.py
src/resource_locator.py
src/runtime.py
src/semantic_analyzer.py
src/settings.py
src/settings_backend.py
src/settings_definitions.py
src/simple_keyword_case.py
src/tokens.py
src/usage_tracker.py
src/version.py
src/editing/__init__.py
src/editing/manager.py
src/filesystem/__init__.py
src/filesystem/base.py
src/filesystem/real_fs.py
src/filesystem/sandboxed_fs.py
src/iohandler/__init__.py
src/iohandler/base.py
src/iohandler/console.py
src/iohandler/curses_io.py
src/iohandler/gui.py
src/iohandler/web_io.py
src/ui/__init__.py
src/ui/auto_save.py
src/ui/base.py
src/ui/capturing_io_handler.py
src/ui/cli.py
src/ui/cli_debug.py
src/ui/curses_settings_widget.py
src/ui/curses_ui.py
src/ui/help_macros.py
src/ui/help_widget.py
src/ui/interactive_menu.py
src/ui/keybinding_loader.py
src/ui/keybindings.py
src/ui/keymap_widget.py
src/ui/markdown_renderer.py
src/ui/recent_files.py
src/ui/tk_help_browser.py
src/ui/tk_settings_dialog.py
src/ui/tk_ui.py
src/ui/tk_widgets.py
src/ui/ui_helpers.py
src/ui/variable_sorting.py
src/ui/visual.py
src/ui/web_help_launcher.py
src/ui/web/__init__.py
src/ui/web/codemirror5_editor.py
src/ui/web/nicegui_backend.py
src/ui/web/session_state.py
src/ui/web/web_settings_dialog.py
mbasic-1.0.955.dist-info/METADATA
mbasic-1.0.955.dist-info/WHEEL
mbasic-1.0.955.dist-info/entry_points.txt
mbasic-1.0.955.dist-info/top_level.txt
mbasic-1.0.955.dist-info/RECORD
