Metadata-Version: 2.4
Name: mbasic
Version: 1.0.955
Summary: MBASIC2025 5.21 BASIC language - Independent open-source implementation
Author-email: Aaron Wohl <mbasic@wohl.com>
License: GPL-3.0-or-later
Project-URL: Homepage, https://github.com/avwohl/mbasic
Project-URL: Documentation, https://avwohl.github.io/mbasic/
Project-URL: Repository, https://github.com/avwohl/mbasic
Project-URL: Issues, https://github.com/avwohl/mbasic/issues
Project-URL: Changelog, https://github.com/avwohl/mbasic/blob/main/docs/dev/WORK_IN_PROGRESS.md
Keywords: basic,interpreter,vintage,retro,programming,mbasic,mbasic-5.21,basic-80,cp/m,vintage-computing
Classifier: Development Status :: 5 - Production/Stable
Classifier: Intended Audience :: Developers
Classifier: Intended Audience :: Education
Classifier: Intended Audience :: End Users/Desktop
Classifier: License :: OSI Approved :: GNU General Public License v3 or later (GPLv3+)
Classifier: Operating System :: OS Independent
Classifier: Programming Language :: Python :: 3
Classifier: Programming Language :: Python :: 3.8
Classifier: Programming Language :: Python :: 3.9
Classifier: Programming Language :: Python :: 3.10
Classifier: Programming Language :: Python :: 3.11
Classifier: Programming Language :: Python :: 3.12
Classifier: Programming Language :: Python :: 3.13
Classifier: Topic :: Software Development :: Interpreters
Classifier: Topic :: Software Development :: Compilers
Classifier: Topic :: System :: Emulators
Classifier: Environment :: Console
Classifier: Environment :: Console :: Curses
Requires-Python: >=3.8
License-File: LICENSE
Provides-Extra: curses
Requires-Dist: urwid>=2.0.0; extra == "curses"
Provides-Extra: tk
Provides-Extra: all
Requires-Dist: urwid>=2.0.0; extra == "all"
Provides-Extra: dev
Requires-Dist: pytest>=7.0; extra == "dev"
Requires-Dist: pexpect>=4.8.0; extra == "dev"
Requires-Dist: build>=0.10.0; extra == "dev"
Requires-Dist: twine>=4.0.0; extra == "dev"
Provides-Extra: help
Requires-Dist: python-frontmatter>=1.0.0; extra == "help"
Provides-Extra: docs
Requires-Dist: mkdocs>=1.5.0; extra == "docs"
Requires-Dist: mkdocs-material>=9.4.0; extra == "docs"
Requires-Dist: mkdocs-awesome-pages-plugin>=2.9.0; extra == "docs"
Provides-Extra: full
Requires-Dist: urwid>=2.0.0; extra == "full"
Requires-Dist: pytest>=7.0; extra == "full"
Requires-Dist: pexpect>=4.8.0; extra == "full"
Requires-Dist: python-frontmatter>=1.0.0; extra == "full"
Requires-Dist: mkdocs>=1.5.0; extra == "full"
Requires-Dist: mkdocs-material>=9.4.0; extra == "full"
Requires-Dist: mkdocs-awesome-pages-plugin>=2.9.0; extra == "full"
Dynamic: license-file
